{
  "Unnormalized_Unfiltered (Strict Math)": {
    "Total Instances (Deduped)": 96,
    "Total Evaluated (No generation failures)": 93,
    "Artifact Rate (Garbage Generations)": 0.0339196462898885,
    "Ranking Accuracy (All valid < distractor)": 0.6344086021505376,
    "Ranking Accuracy (Any valid < distractor)": 0.8494623655913979,
    "Mean KL Divergence (Valid Options)": 2.786302710004456,
    "Mean KL Divergence (Distractor)": 5.294276433691756
  },
  "Unnormalized_Cleaned (Math + Heuristic Filter)": {
    "Total Instances (Deduped)": 96,
    "Total Evaluated (No generation failures)": 93,
    "Artifact Rate (Garbage Generations)": 0.0339196462898885,
    "Ranking Accuracy (All valid < distractor)": 0.6021505376344086,
    "Ranking Accuracy (Any valid < distractor)": 0.8494623655913979,
    "Mean KL Divergence (Valid Options)": 2.809296856763539,
    "Mean KL Divergence (Distractor)": 5.3642680298205745
  },
  "Normalized_Unfiltered (Length-Penalized)": {
    "Total Instances (Deduped)": 96,
    "Total Evaluated (No generation failures)": 93,
    "Artifact Rate (Garbage Generations)": 0.0339196462898885,
    "Ranking Accuracy (All valid < distractor)": 0.6236559139784946,
    "Ranking Accuracy (Any valid < distractor)": 0.8494623655913979,
    "Mean KL Divergence (Valid Options)": 0.16205595235349485,
    "Mean KL Divergence (Distractor)": 0.2841719242802515
  },
  "Normalized_Cleaned (Original Script Baseline)": {
    "Total Instances (Deduped)": 96,
    "Total Evaluated (No generation failures)": 93,
    "Artifact Rate (Garbage Generations)": 0.0339196462898885,
    "Ranking Accuracy (All valid < distractor)": 0.6451612903225806,
    "Ranking Accuracy (Any valid < distractor)": 0.8387096774193549,
    "Mean KL Divergence (Valid Options)": 0.1587877065566775,
    "Mean KL Divergence (Distractor)": 0.28726224191879984
  }
}